tensorcheck/__init__.py
tensorcheck/tensorcheck.py
tensorcheck/test.py
tensorcheck-0.0.1.dist-info/METADATA
tensorcheck-0.0.1.dist-info/MIT_LICENSE.txt
tensorcheck-0.0.1.dist-info/WHEEL
tensorcheck-0.0.1.dist-info/top_level.txt
tensorcheck-0.0.1.dist-info/RECORD
